{"xinhu_custfee":{"fields":[{"name":"id","type":"int","explain":"\u8d39\u7528\u5355 by andy.ma","types":"int(11)","dev":null,"isnull":"NO","lens":null},{"name":"htid","type":"int","explain":"\u5408\u540cID","types":"int(11)","dev":"0","isnull":"YES","lens":null},{"name":"htnum","type":"varchar","explain":"\u5408\u540c\u7f16\u53f7[*]","types":"varchar(20)","dev":null,"isnull":"YES","lens":"20"},{"name":"paydt","type":"datetime","explain":"\u4ed8\u8d39\u65e5\u671f","types":"datetime","dev":null,"isnull":"YES","lens":null},{"name":"uid","type":"smallint","explain":"\u64cd\u4f5c\u8005id","types":"smallint(6)","dev":"0","isnull":"YES","lens":null},{"name":"custid","type":"smallint","explain":"\u5ba2\u6237id","types":"smallint(6)","dev":"0","isnull":"YES","lens":null},{"name":"custname","type":"varchar","explain":"\u5ba2\u6237\u540d\u5b57  by andy.ma","types":"varchar(50)","dev":null,"isnull":"YES","lens":"50"},{"name":"optdt","type":"datetime","explain":"\u64cd\u4f5c\u65e5\u671f","types":"datetime","dev":null,"isnull":"YES","lens":null},{"name":"optname","type":"varchar","explain":"\u7ecf\u529e\u4eba[*]","types":"varchar(10)","dev":null,"isnull":"YES","lens":"10"},{"name":"money","type":"decimal","explain":"\u4ed8\u6b3e\u91d1\u989d","types":"decimal(10,2)","dev":"0.00","isnull":"YES","lens":null},{"name":"type","type":"int","explain":"\u8d39\u7528\u7c7b\u578b","types":"int(11)","dev":"0","isnull":"YES","lens":null},{"name":"explain","type":"varchar","explain":"\u8bf4\u660e","types":"varchar(200)","dev":null,"isnull":"YES","lens":"200"},{"name":"createdt","type":"datetime","explain":"\u521b\u5efa\u65f6\u95f4","types":"datetime","dev":null,"isnull":"YES","lens":null},{"name":"createname","type":"varchar","explain":"\u7ecf\u529e\u4eba[*]","types":"varchar(10)","dev":null,"isnull":"YES","lens":"10"},{"name":"createid","type":"smallint","explain":"\u521b\u5efa\u8005id","types":"smallint(6)","dev":"0","isnull":"YES","lens":null},{"name":"depart","type":"varchar","explain":"\u90e8\u95e8[*]  id  by andy.ma","types":"varchar(50)","dev":null,"isnull":"YES","lens":"50"},{"name":"paymtd","type":"int","explain":"\u4ed8\u6b3e\u65b9\u5f0f 1 \u73b0\u91d1 2 \u652f\u7968 3 \u8f6c\u8d26","types":"int(11)","dev":null,"isnull":"YES","lens":null},{"name":"accid","type":"int","explain":"\u4ed8\u6b3e\u8d26\u6237","types":"int(11)","dev":null,"isnull":"YES","lens":null},{"name":"file_content","type":"varchar","explain":"\u9644\u4ef6","types":"varchar(255)","dev":null,"isnull":"YES","lens":"255"},{"name":"comid","type":"smallint","explain":"\u5bf9\u5e94\u5355\u4f4did","types":"smallint(6)","dev":"0","isnull":"YES","lens":null},{"name":"departid","type":"smallint","explain":"\u90e8\u95e8\u7684ID","types":"smallint(6)","dev":null,"isnull":"YES","lens":null},{"name":"optnameid","type":"smallint","explain":"\u7ecf\u529e\u4eba[*\u7684ID","types":"smallint(6)","dev":null,"isnull":"YES","lens":null}],"data":[{"id":"1","htid":"2","htnum":"001","paydt":"2019-01-24 23:46:00","uid":"1","custid":"8","custname":null,"optdt":"2019-12-27 23:47:10","optname":"\u7ba1\u7406\u5458","money":"200.00","type":"1","explain":"\u5408\u540c\u8bf7\u5ba2\u5403\u996d\u996d","createdt":"2019-12-27 23:47:10","createname":"\u7ba1\u7406\u5458","createid":"1","depart":"\u8d22\u52a1\u90e8","paymtd":"3","accid":"1","file_content":null,"comid":"1","departid":"4","optnameid":"17"}]}}