{"xinhu_feelv":{"fields":[{"name":"id","type":"int","explain":"\u53d1\u7968\u7a0e\u7387\u8868 feelv","types":"int(11)","dev":null,"isnull":"NO","lens":null},{"name":"fpname","type":"varchar","explain":"\u53d1\u7968\u540d\u79f0","types":"varchar(255)","dev":null,"isnull":"YES","lens":"255"},{"name":"felv","type":"decimal","explain":"\u5bf9\u5e94\u7684\u8d39\u7387","types":"decimal(11,2)","dev":"0.00","isnull":"YES","lens":null},{"name":"uid","type":"int","explain":"\u7528\u6237uid","types":"int(11)","dev":"0","isnull":"YES","lens":null},{"name":"comid","type":"int","explain":"\u516c\u53f8id","types":"int(11)","dev":null,"isnull":"YES","lens":null}],"data":[{"id":"1","fpname":"\u666e\u901a\u53d1\u7968","felv":"0.03","uid":"1","comid":"1"},{"id":"2","fpname":"\u4e13\u7528\u53d1\u7968","felv":"0.06","uid":"1","comid":"1"},{"id":"3","fpname":"\u6536\u636e","felv":"0.00","uid":"7","comid":"0"},{"id":"4","fpname":"\u589e\u503c\u7a0e\u53d1\u7968","felv":"0.06","uid":"1","comid":"1"},{"id":"5","fpname":"\u589e\u503c\u7a0e","felv":"0.13","uid":"16","comid":"19"},{"id":"6","fpname":"\u589e\u503c\u7a0e\u666e","felv":"0.03","uid":"16","comid":"19"},{"id":"7","fpname":"\u589e\u503c\u7a0e","felv":"0.60","uid":"24","comid":"23"},{"id":"8","fpname":"\u589e\u503c\u7a0e\u666e\u901a\u53d1\u7968","felv":"0.06","uid":"27","comid":"24"},{"id":"9","fpname":"\u589e\u503c\u7a0e\u4e13\u7528\u53d1\u7968","felv":"0.13","uid":"27","comid":"24"},{"id":"10","fpname":"\u6536\u636e","felv":"0.00","uid":"27","comid":"24"},{"id":"11","fpname":"\u589e\u503c\u7a0e\u53d1\u7968","felv":"0.06","uid":"30","comid":"26"},{"id":"12","fpname":"\u589e\u503c\u7a0e\u4e13\u7968","felv":"0.06","uid":"35","comid":"30"},{"id":"13","fpname":"\u589e\u503c\u7a0e\u666e\u7968","felv":"0.03","uid":"35","comid":"30"}]}}